maslib/agent/__pycache__/agent.cpython-312.pyc
maslib/agent/__pycache__/baseagent.cpython-312.pyc
maslib/agent/agent.py
maslib/agent/agent_prompt.py
maslib/agent/baseagent.py
maslib/crew/crew.py
maslib/llm/__pycache__/constants.cpython-312.pyc
maslib/llm/__pycache__/llm.cpython-312.pyc
maslib/llm/constants.py
maslib/llm/llm.py
maslib/messages/__pycache__/assistant.cpython-312.pyc
maslib/messages/__pycache__/base.cpython-312.pyc
maslib/messages/__pycache__/system.cpython-312.pyc
maslib/messages/__pycache__/user.cpython-312.pyc
maslib/messages/assistant.py
maslib/messages/base.py
maslib/messages/system.py
maslib/messages/user.py
maslibpy-0.1.0.dist-info/METADATA
maslibpy-0.1.0.dist-info/WHEEL
maslibpy-0.1.0.dist-info/RECORD
